logging_utils_cli/__init__.py
logging_utils_cli/formatter.py
logging_utils_cli/utils.py
logging_utils_cli-1.0.1.dist-info/LICENSE
logging_utils_cli-1.0.1.dist-info/METADATA
logging_utils_cli-1.0.1.dist-info/WHEEL
logging_utils_cli-1.0.1.dist-info/RECORD
